BloomSky_API-0.3.1.dist-info/DESCRIPTION.rst
BloomSky_API-0.3.1.dist-info/METADATA
BloomSky_API-0.3.1.dist-info/RECORD
BloomSky_API-0.3.1.dist-info/WHEEL
BloomSky_API-0.3.1.dist-info/entry_points.txt
BloomSky_API-0.3.1.dist-info/metadata.json
BloomSky_API-0.3.1.dist-info/top_level.txt
bloomsky_api/__init__.py
bloomsky_api/__main__.py
bloomsky_api/_version.py
bloomsky_api/bloomsky_api.py
bloomsky_api/cli.py
bloomsky_api/exceptions.py
