Metadata-Version: 2.0
Name: BloomSky-API
Version: 0.3.1
Summary: A simple Python client for the BloomSky API.
Home-page: https://github.com/tylerdave/bloomsky-api
Author: Dave Forgac
Author-email: tylerdave@tylerdave.com
License: MIT
Platform: UNKNOWN
Classifier: Development Status :: 2 - Pre-Alpha
Classifier: Intended Audience :: Developers
Classifier: License :: OSI Approved :: MIT License
Classifier: Natural Language :: English
Classifier: Programming Language :: Python :: 2
Classifier: Programming Language :: Python :: 2.7
Classifier: Programming Language :: Python :: 3
Classifier: Programming Language :: Python :: 3.3
Classifier: Programming Language :: Python :: 3.4
Classifier: Programming Language :: Python :: 3.5
Requires-Dist: dateutils
Requires-Dist: requests
Provides-Extra: cli
Requires-Dist: click; extra == 'cli'
Provides-Extra: develop
Requires-Dist: tox; extra == 'develop'
Requires-Dist: pytest; extra == 'develop'
Requires-Dist: pytest-runner; extra == 'develop'
Requires-Dist: responses; extra == 'develop'
Requires-Dist: click; extra == 'develop'
